acl_anthology_py/__init__.py
acl_anthology_py-0.5.1.dist-info/METADATA
acl_anthology_py-0.5.1.dist-info/WHEEL
acl_anthology_py-0.5.1.dist-info/RECORD
